{
  "source": {
    "spreadsheetId": "1eljw6wpcWKclc3D4TTzZ4d6f7uLJYFbyxGo8R2L9buQ",
    "spreadsheetUrl": "https://docs.google.com/spreadsheets/d/1eljw6wpcWKclc3D4TTzZ4d6f7uLJYFbyxGo8R2L9buQ/edit?usp=sharing",
    "sheetName": "Collections",
    "generatedAt": "2026-05-29T08:50:00-04:00",
    "headers": [
      "Collection ID",
      "Collection Title EN",
      "Collection Title CN",
      "Years",
      "Theme",
      "Description EN",
      "Description CN",
      "Priority",
      "Status",
      "Notes"
    ]
  },
  "records": [
    {
      "_row": 2,
      "collectionId": "COL-001",
      "collectionTitleEn": "Early Wartime Woodcuts",
      "collectionTitleCn": "早期戰時木刻",
      "years": "1939–1940",
      "theme": "Wartime Visual Culture",
      "descriptionEn": "Early woodcuts documenting war, displacement, violence, and civilian survival during the Japanese invasion period.",
      "descriptionCn": "記錄戰爭、流亡、暴力與平民生存經驗的早期木刻作品。",
      "priority": "High",
      "status": "Active",
      "notes": "Important international research direction",
      "imageUrlFile": "/images/artworks/GY-ART-1939-Resistance.jpg"
    },
    {
      "_row": 3,
      "collectionId": "COL-002",
      "collectionTitleEn": "Yan’an Visual Culture",
      "collectionTitleCn": "延安視覺文化",
      "years": "1940–1945",
      "theme": "Rural Society and Wartime Culture",
      "descriptionEn": "Works created during the Yan’an period reflecting rural life, social transformation, and wartime experience.",
      "descriptionCn": "延安時期描繪鄉村生活、社會變遷與戰爭經驗的作品。",
      "priority": "Highest",
      "status": "Active",
      "notes": "Core museum canon",
      "imageUrlFile": "/images/artworks/GY-ART-1943-RentReductionMeeting-Master.jpg",
      "imageWidthPx": 2400,
      "imageHeightPx": 1733,
      "imageSizeLabel": "2400 x 1733 px",
      "imageFileSizeBytes": 1886394
    },
    {
      "_row": 4,
      "collectionId": "COL-003",
      "collectionTitleEn": "Folk Graphic Language",
      "collectionTitleCn": "民間圖像語言",
      "years": "1940s–1950s",
      "theme": "Folk Visual Tradition",
      "descriptionEn": "Woodcuts and graphic works influenced by folk art, New Year prints, and popular visual culture.",
      "descriptionCn": "受民間藝術、年畫與大眾視覺文化影響的木刻與圖像作品。",
      "priority": "High",
      "status": "Active",
      "notes": "Collection representative image updated from uploaded folk-style print on 2026-05-28.",
      "imageUrlFile": "/images/artworks/GY-ART-1943-ProtectOurOwnPeoplesArmy-Color-Master.jpg",
      "imageWidthPx": 1705,
      "imageHeightPx": 2400,
      "imageSizeLabel": "1705 x 2400 px",
      "imageFileSizeBytes": 2133719
    },
    {
      "_row": 5,
      "collectionId": "COL-004",
      "collectionTitleEn": "Industrial Modernity",
      "collectionTitleCn": "工業現代性",
      "years": "1949–1960s",
      "theme": "Industry and Reconstruction",
      "descriptionEn": "Industrial-themed prints documenting reconstruction, factories, workers, and postwar modernization.",
      "descriptionCn": "描繪工業建設、工廠、工人與戰後現代化的工業題材作品。",
      "priority": "Medium",
      "status": "Active",
      "notes": "Collection representative image updated from uploaded industrial woodcut on 2026-05-28.",
      "imageUrlFile": "/images/artworks/GY-ART-1949-GiantOfSteelIndustry-Master.jpg",
      "imageWidthPx": 1800,
      "imageHeightPx": 2400,
      "imageSizeLabel": "1800 x 2400 px",
      "imageFileSizeBytes": 1932047
    },
    {
      "_row": 6,
      "collectionId": "COL-005",
      "collectionTitleEn": "Landscape and Memory",
      "collectionTitleCn": "風景與記憶",
      "years": "1960s–1990s",
      "theme": "Landscape and Reflection",
      "descriptionEn": "Landscape-oriented works reflecting memory, poetry, place, and emotional attachment to homeland.",
      "descriptionCn": "以風景、記憶、詩意與故鄉情感為主題的作品。",
      "priority": "Medium",
      "status": "Active",
      "notes": "Important late-period direction",
      "imageUrlFile": "/images/artworks/GY-ART-1979-EarlySpring-Master.jpg",
      "imageMatchStatus": "Verified representative landscape image path",
      "imageWidthPx": 2400,
      "imageHeightPx": 1800,
      "imageSizeLabel": "2400 x 1800 px",
      "imageFileSizeBytes": 2027049
    },
    {
      "_row": 7,
      "collectionId": "COL-006",
      "collectionTitleEn": "Portrait Archive",
      "collectionTitleCn": "古元肖像檔案",
      "years": "1940s–1990s",
      "theme": "Artist Documentation",
      "descriptionEn": "Historical portraits documenting different stages of Gu Yuan’s life and artistic career.",
      "descriptionCn": "記錄古元人生與藝術階段的歷史肖像檔案。",
      "priority": "High",
      "status": "Active",
      "notes": "Archive and exhibition use",
      "imageUrlFile": "/images/portraits/GY-PH-1950s-GuYuanStudioPortrait.jpg"
    },
    {
      "_row": 8,
      "collectionId": "COL-007",
      "collectionTitleEn": "Exhibition Archive",
      "collectionTitleCn": "展覽檔案",
      "years": "2000s–Present",
      "theme": "Museum and Public Memory",
      "descriptionEn": "Exhibition photos, museum activities, lectures, and public engagement related to Gu Yuan’s legacy.",
      "descriptionCn": "與古元藝術遺產相關的展覽、講座、美術館活動與公共傳播檔案。",
      "priority": "High",
      "status": "Active",
      "notes": "Museum context",
      "imageUrlFile": "/images/exhibitions/GY-PH-ExhibitionViewing.jpg"
    },
    {
      "_row": 9,
      "collectionId": "COL-008",
      "collectionTitleEn": "Family Archive",
      "collectionTitleCn": "家族檔案",
      "years": "Multi-generational",
      "theme": "Intergenerational Continuity",
      "descriptionEn": "Family photographs, memories, contributors, and intergenerational cultural continuity connected to Gu Yuan’s legacy.",
      "descriptionCn": "與古元藝術遺產相關的家族照片、記憶、貢獻者與跨代文化傳承。",
      "priority": "Highest",
      "status": "Active",
      "notes": "Living archive system",
      "imageUrlFile": "/images/family/GY-PH-FamilyVisit.jpg"
    }
  ]
}
